LICENSE
MANIFEST.in
README.md
pyproject.toml
setup.py
./pygrnwang/__init__.py
./pygrnwang/ak135fc.py
./pygrnwang/create_edcmp.py
./pygrnwang/create_edcmp_bulk.py
./pygrnwang/create_edgrn.py
./pygrnwang/create_edgrn_bulk.py
./pygrnwang/create_qseis06.py
./pygrnwang/create_qseis06_bulk.py
./pygrnwang/create_qseis2025.py
./pygrnwang/create_qseis2025_bulk.py
./pygrnwang/create_qssp2020.py
./pygrnwang/create_qssp2020_bulk.py
./pygrnwang/create_spgrn.py
./pygrnwang/create_spgrn_bulk.py
./pygrnwang/edcmp2inp.py
./pygrnwang/edgrn2inp.py
./pygrnwang/focal_mechanism.py
./pygrnwang/geo.py
./pygrnwang/obspy_geo.py
./pygrnwang/plot_seismograms.py
./pygrnwang/pytaup.py
./pygrnwang/qseis06inp.py
./pygrnwang/qseis2025inp.py
./pygrnwang/qssp2020inp.py
./pygrnwang/read_by_qssp.py
./pygrnwang/read_edcmp.py
./pygrnwang/read_green_info_spgrn2020.py
./pygrnwang/read_qseis06.py
./pygrnwang/read_qseis06_diff.py
./pygrnwang/read_qseis2025.py
./pygrnwang/read_qssp2020.py
./pygrnwang/read_spgrn.py
./pygrnwang/read_tpts_table.py
./pygrnwang/signal_process.py
./pygrnwang/spgrn2020inp.py
./pygrnwang/utils.py
./pygrnwang/exec/TauP-2.6.1.jar
fortran_src_codes/edcmp2.0_src/dc3d.f
fortran_src_codes/edcmp2.0_src/dc3d0.f
fortran_src_codes/edcmp2.0_src/edcdisc.f
fortran_src_codes/edcmp2.0_src/edcglobal.h
fortran_src_codes/edcmp2.0_src/edcgrn.f
fortran_src_codes/edcmp2.0_src/edcmain.f
fortran_src_codes/edcmp2.0_src/edcoutput.f
fortran_src_codes/edcmp2.0_src/getdata.f
fortran_src_codes/edcmp2.0_src/okada.f
fortran_src_codes/edgrn2.0_src/axb.f
fortran_src_codes/edgrn2.0_src/bessj.f
fortran_src_codes/edgrn2.0_src/bessj0.f
fortran_src_codes/edgrn2.0_src/bessj1.f
fortran_src_codes/edgrn2.0_src/edgbstab.f
fortran_src_codes/edgrn2.0_src/edgglobal.h
fortran_src_codes/edgrn2.0_src/edghask.f
fortran_src_codes/edgrn2.0_src/edgkern.f
fortran_src_codes/edgrn2.0_src/edglayer.f
fortran_src_codes/edgrn2.0_src/edgmain.f
fortran_src_codes/edgrn2.0_src/edgmatinv.f
fortran_src_codes/edgrn2.0_src/edgmatrix.f
pygrnwang.egg-info/PKG-INFO
pygrnwang.egg-info/SOURCES.txt
pygrnwang.egg-info/dependency_links.txt
pygrnwang.egg-info/entry_points.txt
pygrnwang.egg-info/requires.txt
pygrnwang.egg-info/top_level.txt
