Metadata-Version: 2.4
Name: pygrnwang
Version: 1.0.1
Summary: A Python library for computing Coulomb Failure Stress Change.
Author-email: Zhou Jiangcheng <zhoujcpku@outlook.com>
License: MIT License
Project-URL: Homepage, https://github.com/Zhou-Jiangcheng/pygrnwang
Requires-Python: >=3.11
License-File: LICENSE
Requires-Dist: numpy>=2.3.3
Requires-Dist: matplotlib>=3.9.2
Requires-Dist: scipy>=1.16.2
Requires-Dist: pandas>=2.2.3
Requires-Dist: jpype1>=1.5.2
Requires-Dist: tqdm>=4.67.1
Requires-Dist: mpi4py>=3.1.4
Dynamic: license-file
